tidb_vector/__init__.py
tidb_vector/collection.py
tidb_vector/document.py
tidb_vector/store.py
tivector-0.0.0.dist-info/METADATA
tivector-0.0.0.dist-info/WHEEL
tivector-0.0.0.dist-info/top_level.txt
tivector-0.0.0.dist-info/RECORD
